Metadata-Version: 2.1
Name: royaso
Version: 0.0.7
Summary: royaso  package for 163 music ranking download playlists
Home-page: https://github.com/royaso/ok
Author: royaso
Author-email: zhangroyaso@gmail.com
License: UNKNOWN
Platform: UNKNOWN
Classifier: Programming Language :: Python :: 3
Classifier: License :: OSI Approved :: MIT License
Classifier: Operating System :: OS Independent
